flask_rest_jsonapi/__init__.py
flask_rest_jsonapi/api.py
flask_rest_jsonapi/decorators.py
flask_rest_jsonapi/errors.py
flask_rest_jsonapi/exceptions.py
flask_rest_jsonapi/pagination.py
flask_rest_jsonapi/querystring.py
flask_rest_jsonapi/resource.py
flask_rest_jsonapi/schema.py
flask_rest_jsonapi/utils.py
flask_rest_jsonapi/data_layers/__init__.py
flask_rest_jsonapi/data_layers/alchemy.py
flask_rest_jsonapi/data_layers/base.py
flask_rest_jsonapi/data_layers/filtering/__init__.py
flask_rest_jsonapi/data_layers/filtering/alchemy.py
flask_rested_jsonapi-1.0.1.dist-info/LICENSE
flask_rested_jsonapi-1.0.1.dist-info/METADATA
flask_rested_jsonapi-1.0.1.dist-info/WHEEL
flask_rested_jsonapi-1.0.1.dist-info/top_level.txt
flask_rested_jsonapi-1.0.1.dist-info/RECORD
