Metadata-Version: 2.1
Name: flask-rested-jsonapi
Version: 1.0.1
Summary: Flask extension to create REST web api according to JSONAPI 1.0 specification with Flask, Marshmallow                  and data provider of your choice (SQLAlchemy, MongoDB, ...)
Home-page: https://github.com/Alias-Innovations/flask-rested-jsonapi
Author: Alias Innovations Team
Author-email: alias-team@aliasinnov.com
License: MIT
Keywords: web api rest jsonapi flask sqlalchemy marshmallow
Platform: any
Classifier: Framework :: Flask
Classifier: Programming Language :: Python :: 3
Classifier: Programming Language :: Python :: 3.5
Classifier: Programming Language :: Python :: 3.6
Classifier: Programming Language :: Python :: 3.8
Classifier: License :: OSI Approved :: MIT License
Requires-Dist: six
Requires-Dist: Flask
Requires-Dist: marshmallow
Requires-Dist: marshmallow-jsonapi
Requires-Dist: sqlalchemy
Provides-Extra: dev
Requires-Dist: pytest ; extra == 'dev'
Requires-Dist: coveralls ; extra == 'dev'
Requires-Dist: coverage ; extra == 'dev'
Provides-Extra: docs
Requires-Dist: sphinx ; extra == 'docs'
